getsupertab/__init__.py
getsupertab/py.typed
getsupertab-0.1.0.dist-info/METADATA
getsupertab-0.1.0.dist-info/WHEEL
getsupertab-0.1.0.dist-info/RECORD
